a_pandas_ex_fuzzymerge/README.MD
a_pandas_ex_fuzzymerge/__init__.py
a_pandas_ex_fuzzymerge/requirements.txt
a_pandas_ex_fuzzymerge/thirdparty.json
a_pandas_ex_fuzzymerge-0.10.dist-info/LICENSE.rst
a_pandas_ex_fuzzymerge-0.10.dist-info/METADATA
a_pandas_ex_fuzzymerge-0.10.dist-info/WHEEL
a_pandas_ex_fuzzymerge-0.10.dist-info/top_level.txt
a_pandas_ex_fuzzymerge-0.10.dist-info/RECORD
