Metadata-Version: 2.1
Name: a-pandas-ex-fuzzymerge
Version: 0.10
Summary: Merges two DataFrames using fuzzy matching on specified columns
Home-page: https://github.com/hansalemaos/a_pandas_ex_fuzzymerge
Author: Johannes Fischer
Author-email: aulasparticularesdealemaosp@gmail.com
License: MIT
Keywords: merge,dataframe,fuzzy,rapidfuzz
Classifier: Development Status :: 4 - Beta
Classifier: Programming Language :: Python :: 3 :: Only
Classifier: Programming Language :: Python :: 3.10
Classifier: Topic :: Software Development :: Libraries :: Python Modules
Classifier: Topic :: Utilities
License-File: LICENSE.rst
Requires-Dist: numexpr
Requires-Dist: numpy
Requires-Dist: pandas
Requires-Dist: rapidfuzz
